log_retention_compliance/__init__.py
log_retention_compliance/entrypoint.py
log_retention_compliance/updatepricing.py
cloudwatch_log_retention_manager-0.1.4.dist-info/AUTHORS.rst
cloudwatch_log_retention_manager-0.1.4.dist-info/LICENSE.txt
cloudwatch_log_retention_manager-0.1.4.dist-info/METADATA
cloudwatch_log_retention_manager-0.1.4.dist-info/WHEEL
cloudwatch_log_retention_manager-0.1.4.dist-info/entry_points.txt
cloudwatch_log_retention_manager-0.1.4.dist-info/top_level.txt
cloudwatch_log_retention_manager-0.1.4.dist-info/RECORD
