Metadata-Version: 2.1
Name: cloudwatch-log-retention-manager
Version: 0.1.4
Summary: Tooling to manage the Retention Compliance for AWS CloudWatch logs
Home-page: https://github.com/cevoaustralia/cloudwatch-log-retention-manager
Author: Steve Mactaggart
Author-email: steve.mactaggart@cevo.com.au
License: MIT
Platform: any
Classifier: Development Status :: 4 - Beta
Classifier: Programming Language :: Python
Requires-Dist: boto3 (==1.17.56)
Requires-Dist: PyYAML (==5.4.1)
Requires-Dist: importlib-metadata ; python_version < "3.8"
Provides-Extra: testing
Requires-Dist: setuptools ; extra == 'testing'
Requires-Dist: pytest ; extra == 'testing'
Requires-Dist: pytest-cov ; extra == 'testing'
